commands/__init__.py
commands/commands.py
commands/exceptions.py
commands/factories.py
commands/payloads.py
tests/__init__.py
tests/conftest.py
tests/test__init__.py
tests/test_commands.py
tests/test_exceptions.py
tests/test_factories.py
tests/test_payloads.py
slacktools_commands-1.0.0.dist-info/LICENSE
slacktools_commands-1.0.0.dist-info/METADATA
slacktools_commands-1.0.0.dist-info/WHEEL
slacktools_commands-1.0.0.dist-info/top_level.txt
slacktools_commands-1.0.0.dist-info/RECORD
